ticstat/__init__.py
ticstat/ticstat.py
ticstat-0.1.0.dist-info/LICENSE
ticstat-0.1.0.dist-info/METADATA
ticstat-0.1.0.dist-info/WHEEL
ticstat-0.1.0.dist-info/RECORD
